{
  "metadata": {
    "title": "Effect of Ⅲ B metals (Sc, Y, La and Ce) on active components regulation of VPO catalyst in <ce:italic>n</ce:italic>-butane selective oxidation",
    "authors": "; ; ",
    "journal": "Molecular Catalysis",
    "date": "2023-08-31",
    "doi": "10.1016/j.mcat.2023.113318",
    "abstract": "",
    "uri": "https://api.elsevier.com/content/article/pii/S2468823123004029",
    "pii": "S2468823123004029"
  },
  "fulltext": {
    "full-text-retrieval-response": {
      "scopus-eid": "2-s2.0-85162166446",
      "originalText": "serial JL 315758 291210 291744 291790 291809 31 Molecular Catalysis MOLECULARCATALYSIS 2023-06-17 2023-06-17 2023-06-17 2023-06-17 2023-11-16T15:56:12 1-s2.0-S2468823123004029 S2468-8231(23)00402-9 S2468823123004029 10.1016/j.mcat.2023.113318 S300 S300.2 FULL-TEXT 1-s2.0-S2468823123X00133 2023-11-16T16:10:46.799211Z 0 0 20230801 20230831 2023 2023-06-17T10:52:01.994367Z absattachment articleinfo articlenumber articletitlenorm authfirstinitialnorm authfirstsurnamenorm cid cids contenttype copyright crossmark dateloaded dateloadedtxt datesearch datesort dateupdated dco docsubtype doctype doi eid ewtransactionid hubeid indexeddate issn issnnorm itemstage itemtransactionid itemweight openaccess openarchive pg pgfirst pii piinorm pubdateend pubdatestart pubdatetxt pubyr sectiontitle sortorder srctitle srctitlenorm srctype ssids alllist content subj subheadings suppl tomb volfirst volissue volumelist webpdf webpdfpagecount yearnav figure table body acknowledge affil articletitle auth authfirstini authfull authkeywords authlast grantnumber grantsponsor grantsponsorid highlightsabst primabst ref specialabst 2468-8231 24688231 true 547 547 C Volume 547 30 113318 113318 113318 202308 August 2023 2023-08-01 2023-08-31 2023 Regular Papers article fla © 2023 Elsevier B.V. All rights reserved. EFFECTBMETALSSCYLACEACTIVECOMPONENTSREGULATIONVPOCATALYSTINNBUTANESELECTIVEOXIDATION LI W Introduction Experimental section Catalysts synthesis methods Characterization methods Catalyst test methods Results and discussion Characterization results of catalysts Catalytic performance Discussion Conclusion CRediT authorship contribution statement Acknowledgments References FAIZAN 2022 27 67 M SCHULZ 2018 5523 5532 C MULLER 2020 M ZHANG 2021 15056 15063 X FAIZAN 2021 M WANG 2021 B ZIOLEK 2003 47 64 M HUTCHINGS 2004 G FENG 2007 166 176 R WANG 2010 25 32 F LEONG 2011 341 346 L TAUFIQYAP 2011 635 638 Y WENG 2011 W TAUFIQYAP 2014 270 276 Y ZAZHIGALOV 2014 380 389 V BERENGUER 2016 266 273 R DAI 2018 4515 4525 F LI 2018 51 56 J NASERI 2018 477 495 M WANG 2018 12055 12060 Y HE 2019 2857 2867 B HE 2019 662 669 B LI 2019 K NGUYENDINH 2019 638 651 M SHCHERBAN 2019 975 985 N WANG 2019 5958 5966 Y ZHANG 2019 1126 1130 Q DAI 2020 255 266 F HE 2020 3743 3753 B SHI 2020 6907 6917 Y FAIZAN 2022 M ZHANG 2022 3850 3859 H LI 2023 W DUARTEDEFARIAS 2002 238 246 A PIERINI 2005 197 204 B ZENG 2005 119 122 L SARTONI 2006 L ROWNAGHI 2009 504 516 A TAUFIQYAP 2009 327 334 Y TAUFIQYAP 2010 136 148 Y TAUFIQYAP 2010 997 1012 Y LUCIANI 2011 200 206 S CALDARELLI 2014 419 427 A WU 2015 243 249 H GOO 2019 94 102 K CALDARELLI 2010 204 210 A VU 2011 214 220 B SHANG 2021 12811 12820 Q ZHANG 2013 94 104 Y LIU 2021 58 65 J KALEVARU 2011 52 62 V WU 2016 1 8 H ZHANG 2021 23558 23563 X ZHANG 2021 513 521 T MOTA 2000 308 318 S FREY 2010 131 139 J CHENG 2013 4600 4603 M SCHULZ 2019 113 119 C LIX2023X113318 LIX2023X113318XW 2025-06-17T00:00:00.000Z 2025-06-17T00:00:00.000Z http://creativecommons.org/licenses/by-nc-nd/4.0/ © 2023 Elsevier B.V. All rights reserved. 2023-10-10T17:20:56.083Z http://vtw.elsevier.com/data/voc/AddOnTypes/50.7/aggregated-refined Shanxi Provincial Postdoctoral Science Foundation http://data.elsevier.com/vocabulary/SciValFunders/100017946 http://sws.geonames.org/1814991 Natural Science Foundation of Shanxi Province 20210302123007 202203021212005 2023SHB001 Natural Science Foundation of Shanxi Province http://data.elsevier.com/vocabulary/SciValFunders/501100004480 http://sws.geonames.org/1814991/ 202005D121002 Shanxi Province Science and Technology Department http://data.elsevier.com/vocabulary/SciValFunders/501100013318 http://sws.geonames.org/1814991 Shanxi Science and Technology Major Project The authors gratefully acknowledge financial support from Shanxi Science and Technology Major Project ( 202005D121002 ), the Natural Science Foundation of Shanxi Province ( 202203021212005 , 20210302123007 ) and Shanxi Province PhD project ( 2023SHB001 ). https://doi.org/10.15223/policy-017 https://doi.org/10.15223/policy-037 https://doi.org/10.15223/policy-012 https://doi.org/10.15223/policy-029 https://doi.org/10.15223/policy-004 item S2468-8231(23)00402-9 S2468823123004029 1-s2.0-S2468823123004029 10.1016/j.mcat.2023.113318 315758 2023-11-16T16:10:46.799211Z 2023-08-01 2023-08-31 1-s2.0-S2468823123004029-main.pdf https://s3-eu-west-1.amazonaws.com/prod-ucs-content-store-eu-west/content/pii:S2468823123004029/MAIN/application/pdf/6ffc915bed71e48ee3abe4a75338d851/main.pdf main.pdf pdf true 4568854 MAIN 7 1-s2.0-S2468823123004029-main_1.png https://s3-eu-west-1.amazonaws.com/prod-ucs-content-store-eu-west/content/pii:S2468823123004029/PREVIEW/image/png/64ed847d11a1f05f67d347276db0b111/main_1.png main_1.png png 59358 849 656 IMAGE-WEB-PDF 1 1-s2.0-S2468823123004029-gr1.jpg https://s3-eu-west-1.amazonaws.com/prod-ucs-content-store-eu-west/content/pii:S2468823123004029/gr1/DOWNSAMPLED/image/jpeg/d835bde4d6e4b95e25e6b3c3cc1fc922/gr1.jpg gr1 gr1.jpg jpg 77149 298 565 IMAGE-DOWNSAMPLED 1-s2.0-S2468823123004029-gr7.jpg https://s3-eu-west-1.amazonaws.com/prod-ucs-content-store-eu-west/content/pii:S2468823123004029/gr7/DOWNSAMPLED/image/jpeg/500a34f233b346a48b28f2f3f3dad054/gr7.jpg gr7 gr7.jpg jpg 35512 216 565 IMAGE-DOWNSAMPLED 1-s2.0-S2468823123004029-gr6.jpg https://s3-eu-west-1.amazonaws.com/prod-ucs-content-store-eu-west/content/pii:S2468823123004029/gr6/DOWNSAMPLED/image/jpeg/5b984ca4937681f5c16f8fe6e233d925/gr6.jpg gr6 gr6.jpg jpg 33453 202 565 IMAGE-DOWNSAMPLED 1-s2.0-S2468823123004029-gr5.jpg https://s3-eu-west-1.amazonaws.com/prod-ucs-content-store-eu-west/content/pii:S2468823123004029/gr5/DOWNSAMPLED/image/jpeg/83c21ce5f51bd219993b9b0cc0a7eba5/gr5.jpg gr5 gr5.jpg jpg 41584 304 320 IMAGE-DOWNSAMPLED 1-s2.0-S2468823123004029-gr4.jpg https://s3-eu-west-1.amazonaws.com/prod-ucs-content-store-eu-west/content/pii:S2468823123004029/gr4/DOWNSAMPLED/image/jpeg/ab0fd83640526fd633d6647feae98ec6/gr4.jpg gr4 gr4.jpg jpg 67755 313 527 IMAGE-DOWNSAMPLED 1-s2.0-S2468823123004029-gr3.jpg https://s3-eu-west-1.amazonaws.com/prod-ucs-content-store-eu-west/content/pii:S2468823123004029/gr3/DOWNSAMPLED/image/jpeg/ea40dfc037b39d6e4fb6436f08ec136e/gr3.jpg gr3 gr3.jpg jpg 42014 335 386 IMAGE-DOWNSAMPLED 1-s2.0-S2468823123004029-gr2.jpg https://s3-eu-west-1.amazonaws.com/prod-ucs-content-store-eu-west/content/pii:S2468823123004029/gr2/DOWNSAMPLED/image/jpeg/5cdc20248525dc52035cbfb8161935ba/gr2.jpg gr2 gr2.jpg jpg 98554 564 565 IMAGE-DOWNSAMPLED 1-s2.0-S2468823123004029-ga1.jpg https://s3-eu-west-1.amazonaws.com/prod-ucs-content-store-eu-west/content/pii:S2468823123004029/ga1/DOWNSAMPLED/image/jpeg/d0722fb830b7f20ecd159e2302e07dc9/ga1.jpg ga1 true ga1.jpg jpg 32815 200 356 IMAGE-DOWNSAMPLED 1-s2.0-S2468823123004029-gr1.sml https://s3-eu-west-1.amazonaws.com/prod-ucs-content-store-eu-west/content/pii:S2468823123004029/gr1/THUMBNAIL/image/gif/4c1f2301fe8dba04a7fcc5a9707a9fb2/gr1.sml gr1 gr1.sml sml 21347 115 219 IMAGE-THUMBNAIL 1-s2.0-S2468823123004029-gr7.sml https://s3-eu-west-1.amazonaws.com/prod-ucs-content-store-eu-west/content/pii:S2468823123004029/gr7/THUMBNAIL/image/gif/43ab0b95ce47577975e4205a0e20e60a/gr7.sml gr7 gr7.sml sml 7737 84 219 IMAGE-THUMBNAIL 1-s2.0-S2468823123004029-gr6.sml https://s3-eu-west-1.amazonaws.com/prod-ucs-content-store-eu-west/content/pii:S2468823123004029/gr6/THUMBNAIL/image/gif/b05c5a94ca45a84b3f5c1c61fa9b4bf1/gr6.sml gr6 gr6.sml sml 7347 78 219 IMAGE-THUMBNAIL 1-s2.0-S2468823123004029-gr5.sml https://s3-eu-west-1.amazonaws.com/prod-ucs-content-store-eu-west/content/pii:S2468823123004029/gr5/THUMBNAIL/image/gif/77d4dd1a91272842cc4197362f41fc6d/gr5.sml gr5 gr5.sml sml 11907 164 172 IMAGE-THUMBNAIL 1-s2.0-S2468823123004029-gr4.sml https://s3-eu-west-1.amazonaws.com/prod-ucs-content-store-eu-west/content/pii:S2468823123004029/gr4/THUMBNAIL/image/gif/51ccbfdc8b39e70238d524ffdda35f4b/gr4.sml gr4 gr4.sml sml 13754 130 219 IMAGE-THUMBNAIL 1-s2.0-S2468823123004029-gr3.sml https://s3-eu-west-1.amazonaws.com/prod-ucs-content-store-eu-west/content/pii:S2468823123004029/gr3/THUMBNAIL/image/gif/251b7c6fe27aae974d32a9b36e1535ff/gr3.sml gr3 gr3.sml sml 10029 164 189 IMAGE-THUMBNAIL 1-s2.0-S2468823123004029-gr2.sml https://s3-eu-west-1.amazonaws.com/prod-ucs-content-store-eu-west/content/pii:S2468823123004029/gr2/THUMBNAIL/image/gif/584dafe736ef621ea88af20d0ecf180f/gr2.sml gr2 gr2.sml sml 16147 164 164 IMAGE-THUMBNAIL 1-s2.0-S2468823123004029-ga1.sml https://s3-eu-west-1.amazonaws.com/prod-ucs-content-store-eu-west/content/pii:S2468823123004029/ga1/THUMBNAIL/image/gif/08023fce824941e5aa5a7158ce901982/ga1.sml ga1 true ga1.sml sml 14943 123 219 IMAGE-THUMBNAIL 1-s2.0-S2468823123004029-gr1_lrg.jpg https://s3-eu-west-1.amazonaws.com/prod-ucs-content-store-eu-west/content/pii:S2468823123004029/HIGHRES/image/jpeg/153fde1dbe3086adc69cd0c0af63f154/gr1_lrg.jpg gr1 gr1_lrg.jpg jpg 593191 1317 2500 IMAGE-HIGH-RES 1-s2.0-S2468823123004029-gr7_lrg.jpg https://s3-eu-west-1.amazonaws.com/prod-ucs-content-store-eu-west/content/pii:S2468823123004029/HIGHRES/image/jpeg/df5e76ca280e777a711d332955c8a0bd/gr7_lrg.jpg gr7 gr7_lrg.jpg jpg 218837 957 2500 IMAGE-HIGH-RES 1-s2.0-S2468823123004029-gr6_lrg.jpg https://s3-eu-west-1.amazonaws.com/prod-ucs-content-store-eu-west/content/pii:S2468823123004029/HIGHRES/image/jpeg/224f0f50c31b782804432ba3902e6e66/gr6_lrg.jpg gr6 gr6_lrg.jpg jpg 206018 893 2500 IMAGE-HIGH-RES 1-s2.0-S2468823123004029-gr5_lrg.jpg https://s3-eu-west-1.amazonaws.com/prod-ucs-content-store-eu-west/content/pii:S2468823123004029/HIGHRES/image/jpeg/1926171a4277be9526f787bfc725c48b/gr5_lrg.jpg gr5 gr5_lrg.jpg jpg 264594 1348 1417 IMAGE-HIGH-RES 1-s2.0-S2468823123004029-gr4_lrg.jpg https://s3-eu-west-1.amazonaws.com/prod-ucs-content-store-eu-west/content/pii:S2468823123004029/HIGHRES/image/jpeg/636889ef3d46793a856653a8a57a6774/gr4_lrg.jpg gr4 gr4_lrg.jpg jpg 470023 1386 2333 IMAGE-HIGH-RES 1-s2.0-S2468823123004029-gr3_lrg.jpg https://s3-eu-west-1.amazonaws.com/prod-ucs-content-store-eu-west/content/pii:S2468823123004029/HIGHRES/image/jpeg/bab11a30f15af34ffd703e16a2ca4d63/gr3_lrg.jpg gr3 gr3_lrg.jpg jpg 245999 1483 1708 IMAGE-HIGH-RES 1-s2.0-S2468823123004029-gr2_lrg.jpg https://s3-eu-west-1.amazonaws.com/prod-ucs-content-store-eu-west/content/pii:S2468823123004029/HIGHRES/image/jpeg/8f81d4ab70a5796a5aee8f5979f059d4/gr2_lrg.jpg gr2 gr2_lrg.jpg jpg 738945 2495 2500 IMAGE-HIGH-RES 1-s2.0-S2468823123004029-ga1_lrg.jpg https://s3-eu-west-1.amazonaws.com/prod-ucs-content-store-eu-west/content/pii:S2468823123004029/HIGHRES/image/jpeg/4598ad26b3810917a6c7aa08460dfbe6/ga1_lrg.jpg ga1 true ga1_lrg.jpg jpg 265825 886 1576 IMAGE-HIGH-RES 1-s2.0-S2468823123004029-am.pdf https://s3-eu-west-1.amazonaws.com/prod-ucs-content-store-eu-west/content/egi:10D6Q20V3D0/MAIN/application/pdf/e4c686865866d6a1c2969df250156d70/am.pdf am am.pdf pdf false 586334 AAM-PDF MCAT 113318 113318 S2468-8231(23)00402-9 10.1016/j.mcat.2023.113318 Elsevier B.V. Fig. 1 SEM images of PVPO and M-PVPO (a), VPO and M-VPO catalysts (b) and TG-DTG profiles of PVPO and M-PVPO (c). Fig. 1 Fig. 2 XRD patterns of PVPO and M-PVPO (a) and VPO and M-VPO catalysts (b); Raman patterns of PVPO and M-PVPO (c) and VPO and M-VPO catalysts(d). Fig. 2 Fig. 3 The H2-TPR spectra of all the activated VPO catalysts. Fig. 3 Fig. 4 XPS spectra of V 2p3/2 (a) and O 1 s (b) of all VPO catalysts. Fig. 4 Fig. 5 The NH3-TPD profiles of VPO and M-VPO catalysts. Fig. 5 Fig. 6 The variation of the weak (a) and medium(b) acid sites of VPO and M-VPO catalysts with the V5+/V4+ ratio. (The V5+/V4+ ratio come from XPS result). Fig. 6 Fig. 7 The variation of the weak (a) and medium(b) acid sites of all the activated VPO catalysts with n-butane conversion. Fig. 7 Table 1 All VPO catalysts surface areas and XRD data for all PVPO and VPO catalysts. Table 1 Catalyst Surface area(m2/g) I(001)/I(220) a of the corresponding precursors I(200)/I(024) a FWHM Crystallite size b (nm) (200) (200) Bulk VPO 13.6 0.73 0.73 0.75 11.2 Sc-VPO 12.1 0.83 0.86 1.11 7.7 Y-VPO 13.0 0.99 0.83 1.99 4.3 La-VPO 14.1 0.82 0.74 1.61 5.3 Ce-VPO 15.0 0.64 0.79 1.92 4.4 a Relative peak intensities ratio. b Calculated by means of the Debye-Scherrer formula. Table 2 The reduction properties of VPO and M-VPO catalysts. Table 2 Catalyst H2-TPR result peak Tm ( °C) O atom removed from catalysts (mmol/g) Ratio for O removal of V5+/V4+ Bulk VPO 1 521 1.45 1.00 2 745 1.45 total 2.90 Sc-VPO 1 503 0.94 0.87 2 754 1.08 total 2.02 Y-VPO 1 502 1.07 0.82 2 757 1.31 total 2.38 La-VPO 1 493 1.22 1.03 2 747 1.18 total 2.41 Ce-VPO 1 516 1.40 1.05 2 768 1.34 total 2.73 Table 3 XPS results of all the activated VPO catalysts. Table 3 Catalyst XPS results Lat-O/Sur-O V 2p3/2 (eV) P 2p(eV) O 1s V5+/V4+ Vox P/V Bulk VPO 10.86 517.37 134.20 531.53 0.53 4.35 1.44 Sc-VPO 14.61 517.31 134.18 531.41 0.44 4.31 2.50 Y-VPO 13.45 517.26 134.15 531.49 0.48 4.33 1.50 La-VPO 9.45 517.31 134.17 531.53 0.58 4.37 1.56 Ce-VPO 12.89 517.24 134.06 531.42 0.53 4.35 1.52 Using the following correlation: Vox= [5*(V5+%) +4* (V4+%)]. Table 4 Acid sites distribution of VPO and M-VPO catalysts from NH3-TPD results. Table 4 Catalyst Acid sites distribution, n(NH3)/(mmol/g) weak medium strong total VPO 0.05 0.09 0.09 0.23 Sc-VPO 0.03 0.06 0.05 0.14 Y-VPO 0.03 0.07 0.08 0.18 La-VPO 0.06 0.11 0.09 0.26 Ce-VPO 0.05 0.09 0.08 0.22 Table 5 The catalytic performance of all the used catalysts with an 8-hour time on stream a . Table 5 Catalyst Conv. (%) Sel. (%) YMA (%) MA CO CO2 Bulk VPO 85.61 49.12 28.54 22.34 42.05 Sc-VPO 96.44 47.89 28.07 24.04 46.19 Y-VPO 92.37 60.93 25.87 13.20 56.28 La-VPO 80.80 51.38 29.71 18.91 41.48 Ce-VPO 80.75 48.64 29.50 21.86 39.28 a Reaction conditions: temperature 430°C with 1.1 vol% n-butane under a GHSV of 2000 h − 1. Effect of Ⅲ B metals (Sc, Y, La and Ce) on active components regulation of VPO catalyst in n-butane selective oxidation Wenjiao Li Methodology Investigation Writing – original draft a b Shupeng Guo Formal analysis Writing – review & editing a ⁎ Heqin Guo Formal analysis Writing – review & editing Data curation Resources a Yong Xiao Software Project administration a Litao Jia Supervision Project administration a c ⁎ Debao Li Supervision Project administration a c a State Key Laboratory of Coal Conversion, Institute of Coal Chemistry, Chinese Academy of Sciences, Taiyuan 030001, Shanxi, PR China State Key Laboratory of Coal Conversion Institute of Coal Chemistry, Chinese Academy of Sciences Taiyuan Shanxi 030001 PR China aState Key Laboratory of Coal Conversion, Institute of Coal Chemistry, Chinese Academy of Sciences, Taiyuan 030001, Shanxi, PR China b University of Chinese Academy of Sciences, Beijing 100049, PR China University of Chinese Academy of Sciences Beijing 100049 PR China bUniversity of Chinese Academy of Sciences, Beijing 100049, PR China c Dalian National Laboratory for Clean Energy, Dalian, 116023, PR China Dalian National Laboratory for Clean Energy Dalian 116023 PR China cDalian National Laboratory for Clean Energy, Dalian, 116023, PR China ⁎ Corresponding authors. Vanadium phosphorus oxide (VPO) catalyst has been modified by the Ⅲ B elements (Sc, Y, La, Ce) have been prepared. Those catalysts were tested in n-butane selective oxidation, and it was shown that Y-VPO catalyst has the highest maleic anhydride (MA) yield among the studied catalysts. The VPO catalyst was characterized by a series of techniques. As evidenced by property characterization in conjunction with catalytic performance, we found that the presence of rare earth metals alters the phase composition of VPO catalyst. And then, the acidity of VPO catalyst was adjusted. Finally, the change of acidity could impact the n-butane activation process, which affected the n-butane conversion. Moreover, the rare earth metals also modulated the ratio of lattice oxygen and surface oxygen and then the MA selectivity. Graphical abstract Image, graphical abstract Keywords Rare earth metal VPO catalyst N-butane oxidation MA Data availability Data will be made available on request. Introduction MA is a high-value-added compound that is mostly produced through the selective oxidation of n-butane [1,2]. Despite being shown to the most efficient industrial catalyst for the selective oxidation of n-butane, VPO catalyst has been demonstrated to be vulnerable to peroxidation, making controlling MA selectivity problematic. The molar yield of MA is remains quite low limited by the selectivity [3–5], which fails to meet the industrial requirements [3,6,7]. As a result, understanding the essential features of VPO catalyst through some ways is critical in order to identify methods for optimizing VPO catalyst. So far, great efforts have been devoted to modifying VPO catalyst to improve MA yield and better understand catalytic behavior. The main methods to optimize catalyst include the development of new catalyst preparation methods and the regulation of catalyst surface properties by the addition of promoters [6,8-34]. Among them, the addition of metal dopants is currently recognized as the most direct and effective way. At present, various metals have been used to modify VPO catalyst, such as Zr, Zn, Mo, Bi, Ni, Mn, Fe, Cu, Co, Ga, Nb, Ce, Cr, Y, Au, Sm, Te, La, etc. [8,12,13,15,23,33-46]. Despite many studies, there is still no consensus on the understanding of the active sites and surface properties of catalyst. The complex structure of VPO catalyst is the primary cause of this condition. The complex VPO catalyst has been found in more than 14 phases with distinguished structural morphology and changeable surface chemical states and so on [26,47]. Therefore, plenty of opportunities exist in the field to optimize the VPO catalyst composition and improve catalytic performance. The understanding of the reaction mechanism can help us optimize the VPO catalyst. The reaction conforms to the REDOX mechanism. In short, n-butane is first dehydrogenated to form butene or butadiene, and then MA is formed by the epoxide of three oxygen atoms. The rate-controlled step is the process of dehydrogenation step for the reaction. Therefore, we need to accelerate the step of activating CH bond, and then accelerate the dehydrogenation process. Many researches show that rare earth metals (Sc, Y La, Ce,) is often used as promoters or supports to enhance the catalytic performance of low carbon alkanes dehydrogenation [20,48]. Shang et al. [49] investigated the impact of Scandium (Sc) on catalytic performance for the propane dehydrogenation reaction. And they found the introduce of Sc promotes the formation of oxygen vacancies and active sites, thus enhancing the catalytic performance evidently. Zhang et al. [50] synthesized La-doped mesoporous alumina for propane dehydrogenation, and the substance served as the support of platinum–tin catalyst. The outcome demonstrated that adding La improves the efficiency of the catalytic process. This might be due to introduction of La encouraged the distribution of metallic particles. In addition, ZnAl2O4 modified by Y, La, Ce was used to support PtSn and the catalyst was tested in isobutane dehydrogenation process [51]. The three metals incorporate into ZnAl2O4 matrix in different ways and affect the acidity of the support. The positive role of Sc, Y La, Ce in the dehydrogenation oxidation of alkanes was observed. Combined with the requirement of the active sites and the essential nature of promoters Sc, Y La, Ce, modifying VPO catalyst with Sc, Y La, Ce is a good way to explore the catalytic mechanism. Furthermore, to the best of our knowledge, no research has been conducted on the use of congener rare earth metals as modifiers to enhance the catalytic performance. With the above considerations, this work attempts to use the Ⅲ B elements to modify VPO catalyst. The catalytic performance in relation to the effects of various metal additions on the VPO catalyst is studied systematically. The relationship between the catalytic activity and the performance characteristics of VPO catalyst modified by the III B metal elements were proposed to be related. Experimental section Catalysts synthesis methods The bulk VPO precursor (PVPO) and VPO precursors modified by metals (M-PVPO) were obtained as the literature [34]. The preparation process is as follows: V2O5 was dissolved in a mixture of isobutanol and benzyl alcohol. Phosphoric acid was added to the mixture after reflux. After further reflux, the resulting solution was filtered, washed and dried. The M-PVPO is prepared by adding a certain amount of ScN3O9·6H2O, YN3O9·6H2O, LaN3O9·6H2O and CeN3O9·6H2O with V2O5 in the first step, respectively. The M/V atomic ratio is 0.01. The obtained powders are denoted as M-PVPO (M=Sc, Y, La and Ce). The bulk VPO catalyst and metal-modified VPO (M-VPO) catalysts were prepared in the method [34]: the PVPO and M-PVPO were formed into purpose particles (20–40 mesh). Afterwards, precursor enclosed in a quartz tube was activated in-situ. Raising the temperature to 430 °C in the mixture gas of 1.1% n-butane in air and keep the temperature for a period of time. Correspondingly, the obtained powders were named as bulk VPO catalyst and M-VPO (M= Sc, Y, La and Ce) catalyst. Characterization methods TG is conducted on a SETSYS EVOLUTION TGA 16/18 thermal analyzer. The TG and DTG of all precursors are measured. XRD analyzer (PANalytical X'pert3) with monochromatized CuKα radiation is used to determine the structural characteristics of all precursors and catalysts. With the use of the LabRAM HR Evolution Raman equipment, Raman spectra are captured. The excitation source is the Ar ion laser's 325 nm line. The morphological of all precursors and catalysts are obtained by a SEM device (JSM-7900F) with an acceleration voltage of 5 kV. In order to obtain the information of the textural properties of catalyst, a MicroActive ASAP 2460 devices are carried out. AXIS ULTRADLD XPS is used to examine the chemical characteristics. XPSPEAK41 software is used to fit the O 1 s and V 2p3/2 spectra of all samples. The peaks are resolved using model functions with 90% Gaussian and 10% Lorentzian. The H2-TPR experiments are measured by multipurpose automatic adsorption instrument (FINESORB-3010D). The activated VPO catalyst is pretreated of 1 h at 100°C in Ar atmosphere. The sample is then cooled to room temperature. Subsequently, in a 5% H2/Ar gas the catalyst is heated to 850°C until the reduction was complete. TCD detector is used to recorded the consumption of H2. The elements content on the VPO catalyst surface is calibrated by the standard of reduction of CuO. NH3-TPD is performed by XIANQUAN5080B. The activated catalyst (100 mg) is pre-treated for 1 h in He atmosphere at 200°C. The catalyst is cooled to room temperature. Then the obtained sample is adsorbed in 10% NH3/He mixture. Finally, the sample is heated to 500°C in He air. The exhaled gas was detected by TCD detector. Catalyst test methods The selective oxidation of n-butane was tested in a continuous flow fixed bed reactor. After in situ activation, the VPO catalyst of 20–40 mush continued to react under activation conditions, and the outlet gas generated was analyzed by online chromatography. Carbon mass balances were better than 95% typically. Results and discussion Characterization results of catalysts Fig. 1 presents the SEM micrographs of the PVPO (a) and VPO catalysts (b). It shows that the bulk VPO precursor exhibits the flaky platelets, while the Sc-, Y-, La- and Ce-modified precursors exhibits rosette plate-like structure. The bulk VPO, La-VPO and Sc-VPO catalysts presents a disordered stacked blocky structure, while the Sc- and Y-modified catalysts still maintain the hierarchical structure. TG analysis and DTA are depicted in Fig. 1(c). From Fig. 1(c), the weight loss curves underwent three steps for all catalysts [11,52,53]. The first two step occurs at 150 and 350°C [34,53]. The former arises from the desorption of physically adsorbed water. The latter originates from the elimination of alcohols from the precursor layers and the conversion of VOHPO4·0·5H2O to (VO)2P2O7. Crystal defects may be the cause of the third stage above 430 °C [52,53]. The decomposition temperature of all M-PVPO is higher than bulk VPO precursor. And the decomposition temperature of Y-PVPO and Sc-PVPO is relatively high. That may lead to the Y-PVPO and Sc-PVPO maintain a good morphology after activation. The result and the SEM findings are in good accord. To further investigate the difference in catalyst structure, the crystallographic structure of all the PVPO and VPO catalysts are analyzed through XRD and Raman. The XRD patterns of all PVPO and all VPO catalysts are shown in Fig. 2 (a) and (b). Fig. 2(a) illustrates that all the PVPO exhibit the characteristic diffraction peaks at 2θ=15.8°, 19.9°, 24.5°, 27.3°, 30.7°, corresponding to the (001), (101), (021), (121) and (220) planes of VOHPO4 0·0·5H2O [21,27,54], respectively. Fig. 2(b) demonstrates that the main peaks at 2θ=18.4°, 23°, 28.6° and 30.0°, which are related to the (020), (200), (024) and (032) planes of (VO)2P2O7 [43,54], respectively. Interestingly, the predominant crystalline phase for the bulk VPO catalyst is (VO)2P2O7 phase. However, the peaks assigned to VOPO4 phase are detected for Sc-, Y-, La-, Ce-VPO catalysts. The peaks are assigned to the characteristic peaks of δ-VOPO4 phase [21], αⅡ-VOPO4 phase at 22.3° and 24.4° as well as 25.1° and 29.2° [27]. According to the literatures [22,39,41,45], the (VO)2P2O7 (200) surface is the active plane of VPO catalyst. The plane is topologically transformed from the VOHPO4 0·0·5H2O (001) surface. The relative strength of the (001) surface is consistent with the exposure of the surface (220). Therefore, Table 1 lists the I(001)/I(220) of PVPO and I(200)/I(024) ratio of VPO catalysts. Raman spectra of all PVPO and the activated VPO catalysts give more information about the crystal structure. As shown in Fig. 2(c) and (d), the main bands of all precursors emerged at 986, 1106, 1053 cm−1 are attributed to VOHPO4·0·5H2O [22]. It was reported that VOPO4 phases are found in the band at 468, 598, 941, 1018, and 1090 cm−1, whereas (VO)2P2O7 phase are found at 443, 467, 588, and 1016 cm−1. The emergence of novel VOPO4 phases for Sc-, Y-, La- and Ce-VPO catalysts. Novel VOPO4 phases were ascribed to the β-VOPO4 phase (443 and 467 cm−1), the αⅡ-VOPO4 or δ-VOPO4 phase (1016 cm−1), as well as the γ-VOPO4 or αⅡ-VOPO4 phase (1090 cm−1) [7,30,55]. According to the literatures, the formation of MA is mainly affected by the V5+ phase [7,12,40,44,46,56-59]. A certain amount of δ-VOPO4 phase promoted the formation of MA, while αII-VOPO4 phase inhibited the formation of MA [44,56]. Of course, it is also suggested that the presence of β-VOPO4 phases can enhance the catalytic activity and promote the n-butane conversion [12,46,54,59]. The XRD and Raman results suggest that the introduce of rare earth metal facilitates the formation of δ-VOPO4 phase, as well as the potential formation of αII-VOPO4 phase and β-VOPO4 phases. Therefore, the rare earth modified VPO catalyst is likely to affect the selective oxidation. H2-TPR experiments are carried out to learn more about the vanadium oxidation state and the different oxygen species. Fig. 3 shows the TPR spectra of all activated VPO catalysts. Fig. 3 shows that all catalysts exhibit two major peaks in the region of 493–521°C and 745–768°C, respectively [23,24,29,46]. Generally, the reduction of lattice oxygen caused by the V5+ and V4+ phase can be attributed to the peaks at lower and higher temperatures, respectively [5,22]. For bulk VPO catalyst, the first peak appears at 521°C, which shift to lower temperature for modified VPO catalysts. The result means that it is easy to be reduced for the V5+ phase of modified VPO catalysts. The total reduction property of all activated catalysts from TPR results are listed in Table 2 . It can be observed that the oxygen atoms removal ratio of V5+/V4+ decreases for Sc-, Y-modified catalysts. While that almost unchanged for La-, Ce-modified catalysts. XPS measurements are furthermore performed to obtain more information about the surface element chemical states. The V 2p3/2 peak at 517.4 and 518.7 eV is typically associated with the V4+ and V5+ phase [32,34], respectively. VPO catalyst is a mixture of V4+ and V5+ phase from Fig. 4 (a). The V5+/V4+ ratio is calculated (Table 3 ). As summarized in Table 3, the surface V5+/V4+ atomic ratio of Sc-, Y-modified VPO catalysts decreases, while that for La-, Ce-modified VPO catalysts increases. The results illustrate that the introduce of rare earth metals can modify the surface vanadium oxidation state distribution. The oxygen species on the catalysts surface can be estimated furthermore by XPS. The lattice oxygen and hydroxide ions as well as carbonates is key to VPO catalyst, which is denoted Lat-O and Sur-O, respectively. As indicated in Fig. 4(b), the peaks at 531.0–533.0 eV are ascribed to Lat-O in VPO catalyst, while the peak at 533.0–534.1 eV is ascribed to Sur-O in VPO catalyst [23,29]. The ratio of Lat-O/Sur-O are listed in Table 3. The value increases significantly with the addition of Sc, Y and La. All VPO catalysts have a P-enriched surface, which is a good phenomenon for typical VPO catalyst. It is well known that the enrichment of a certain of P element can improve the catalytic activity [31]. This is because a certain P element enriched on the surface can help to stabilize the active phase and adjust the V5+/V4+ ratio [6,42,43]. It was reported that the surface acidity on catalyst is crucial for the n-butane selective oxidation. Therefore, NH3-TPD is performed to investigate the surface acidity. As seen in Fig. 5 , all the catalysts show three desorption peaks. According to the location of the peak, it can be divided into three acid sites with different intensity. The distribution of surface acid site on VPO catalyst are calculated in Table 4 . As compared to the bulk VPO catalyst, the overall acid sites for Sc- and Y-VPO catalysts decrease. While there is no noticeable variation in total acid sites for La-, Ce-VPO catalysts. Interestingly, it is found that the change of acid sites for the VPO catalyst is in good agreement with the change of V5+phase by XPS and NH3-TPD result. Therefore, it can be possibly concluded that the V5+phase of the catalyst may have contributed to its acidity. So, the relationship between the acid sites and the V5+/V4+ ratio is studied. The correlation between the acid sites and the V5+/V4+ ratio is illustrated in Fig. 6 . Noticeably, it can be seen that the weak and medium acid sites have been proposed to have a significant positive correlation with the V5+/V4+ ratio on VPO catalyst surface, as shown in Fig. 6(a) and (b). Thus, it can be concluded that the V5+/V4+ ratio is the key factor to increasement of the weak and medium acid sites. Catalytic performance The catalytic evaluation for all activated VPO catalysts is carried out in n-butane selective oxidation to MA (see Table 5 ). The bulk VPO catalyst has shown a n-butane conversion of 85.61% and a MA selectivity of 49.12%. Sc-VPO catalyst could significantly improve n-butane conversion when compared to bulk VPO catalyst. Y-VPO catalyst could improve both conversion and selectivity simultaneously. However, La-VPO catalyst slightly increases MA selectivity but at the cost of decreasing conversion. Ce-VPO catalyst reduces conversion and selectivity simultaneously. Among the researched catalysts, the MA yield of 56.28% is achieved on Y-modified VPO catalyst. The findings of the characterization demonstrate that the introduce of rare earth metals considerably alters the phase composition and surface characteristics of catalyst. The introduction of rare earth metals leads to the appearance of δ-, αII- and β-VOPO4 phases in VPO catalyst. The change of VOPO4 phase may be associated with the surface acidity on catalyst. The change of the surface acidity might affect the n-butane dehydrogenation. It is suggested that the suitable amount of VOPO4 phase for Sc-VPO and Y-VPO catalysts result in the suitable the surface acidity, and then result in the high n-butane conversion. Moreover, Y-VPO and La-VPO catalysts show the high MA selectivity because of the selective δ-VOPO4 phase. Discussion As previously mentioned, the weak and medium acidities could be caused by the VOPO4 phase on catalyst. Thus, to try further investigate the impact of surface acid sites on catalytic performance, the relationship between the acid sites and n-butane conversion is explored. As shown in Fig. 7 (a) and (b), the weak and medium acid sites have been proposed to have a negative correlation with the conversion of n-butane. Typically, surface acidity can regulate the adsorption and desorption behavior of n-butane [30,33]. In conclusion, the introduction of rare earth metals leads to the change of V5+ phase, further adjusts the acidity of catalyst, and finally affects the catalytic performance. From XRD and Raman results, there is the formation of new V5+ phases for the M-VPO catalysts. This might indicate that these VPO catalysts promote the diversity of V5+ phases. A certain amount of δ-VOPO4 and β-VOPO4 phase can enhance the activity of VPO catalyst, while αII-VOPO4 phase inhibited the formation of MA [12,46,54,59]. The introduction of rare earth metal may also encourage the creation of the δ-, αII- and β-VOPO4 phases. The H2-TPR and XPS data, however, demonstrate that V5+ phase for Sc, Y-VPO catalysts decrease, while slightly increase for La, Ce-VPO catalysts. Frey et al. [57] demonstrated that n-butane is preferentially adsorbed and activated at sites of δ-VOPO4 phase by quantitative solid-state NMR investigation. Thus, it can be guessed that the addition of Sc and Y moderately increases the δ-VOPO4 phase of VPO catalyst and promotes the activation of n-butane. The introduce of La and Ce can promote the increase of non-selective phase or generate excessive V5+ phase, so their catalytic performance is not satisfactory. Notably, the Sc-VPO and Y-VPO catalysts present higher activity than bulk VPO catalyst, while the La-VPO and Ce-VPO catalysts do not. The activity of VPO catalyst is influenced by several factors. The value of Lat-O/Sur-O ratio for Sc- and Y-VPO catalysts significantly increases. According to our previously study [34], the lattice oxygen from VPO catalyst may promote the process of MA synthesis. Additionally, it is believed that the ratio value of P/V really isn't the most crucial element in determining the catalytic effectiveness of catalyst. Besides, from the SEM and TG results, the structure stability of Sc-PVPO and Y-PVPO catalysts is enhanced. And the bulk VPO possesses plate-like structure, while Sc-VPO and Y-VPO catalysts possess rosette-shape clusters. The rosette-shaped clusters can expose the (200) plane preferentially, which is favorable for MA synthesis [45]. Conclusion In summary, a series of VPO catalysts modified by rare earth metals (Sc, Y, La, and Ce) are prepared. Sc, Y-VPO catalysts show an obvious improvement in n-butane conversion. La, Ce-VPO catalysts show an increase in MA selectivity. Among all used catalysts, Y-VPO catalyst have the highest MA yield. Combined with all the characterization, the reason is analyzed. Firstly, the V5+/V4+ ratio of Y-VPO catalyst decreases compared with bulk VPO catalyst. Then, the acidity of catalyst deceases due to the decrease of the V5+/V4+ on the catalyst surface. Finally, the conversion of n-butane is encouraged by the proper surface acidity. Additionally, the Lat-O/Sur-O ratio has a significant impact on MA selectivity. Thus, Y-VPO catalyst have the highest MA yield in this study because of the increases in both n-butane conversion and MA selectivity simultaneously. CRediT authorship contribution statement Wenjiao Li: Methodology, Investigation, Writing – original draft. Shupeng Guo: Formal analysis, Writing – review & editing. Heqin Guo: Formal analysis, Writing – review & editing, Data curation, Resources. Yong Xiao: Software, Project administration. Litao Jia: Supervision, Project administration. Debao Li: Supervision, Project administration. Declaration of Competing Interest The authors declare that they have no known competing financial interests or personal relationships that could have appeared to influence the work reported in this paper. Acknowledgments The authors gratefully acknowledge financial support from Shanxi Science and Technology Major Project (202005D121002), the Natural Science Foundation of Shanxi Province (202203021212005, 20210302123007) and Shanxi Province PhD project (2023SHB001). References [1] N.F. Dummer, J.K. Bartley, G.J. Hutchings, Vanadium Phosphate Materials as Selective Oxidation Catalysts, in, 2011, pp. 189–247. [2] M. Faizan R. Zhang R. Liu J. Ind. Eng. Chem. 110 2022 27 67 M. Faizan, R. Zhang, R. Liu, J. Ind. Eng. Chem., 110 (2022) 27–67. [3] C. Schulz R. Kraehnert F. Rosowski B. Frank ChemCatChem 10 2018 5523 5532 C. Schulz, R. Kraehnert, F. Rosowski, B. Frank, ChemCatChem, 10 (2018) 5523–5532. [4] M. Müller M. Kutscherauer S. Böcklein G. Mestl T. Turek Chem. Eng. J. 401 2020 M. Müller, M. Kutscherauer, S. Böcklein, G. Mestl, T. Turek, Chem. Eng. J., 401 (2020). [5] X. Zhang H. Wang L. Gou L. Li A. Duan Z. Cao Ind. Eng. Chem. Res. 60 2021 15056 15063 X. Zhang, H. Wang, L. Gou, L. Li, A. Duan, Z. Cao, Ind. Eng. Chem. Res., 60 (2021) 15056–15063. [6] M. Faizan K.U.K. Niazi H. Nawaz N. Muhammad H. Li F. Dai R. Zhang R. Liu S. Zhang Processes 9 2021 M. Faizan, K.U.K. Niazi, H. Nawaz, N. Muhammad, H. Li, F. Dai, R. Zhang, R. Liu, S. Zhang, Processes, 9 (2021). [7] B.J. Wang F. Dai L. Jiang R. Zhang G.W. Chu R. Liu Y. Luo AlChE J. 2021 B.J. Wang, F. Dai, L. Jiang, R. Zhang, G.W. Chu, R. Liu, Y. Luo, AlChE J., (2021). [8] M. Ziolek Catal. Today 78 2003 47 64 M. Ziolek, Catal. Today, 78 (2003) 47–64. [9] G.J. Hutchings J. Mater. Chem. 14 2004 G.J. Hutchings, J. Mater. Chem., 14 (2004). [10] R. Feng X. Yang W. Ji Y. Chen C. Au J. Catal. 246 2007 166 176 R. Feng, X. Yang, W. Ji, Y. Chen, C. Au, J. Catal., 246 (2007) 166–176. [11] F. Wang J.-L. Dubois W. Ueda Appl. Catal. A 376 2010 25 32 F. Wang, J.-L. Dubois, W. Ueda, Appl. Catal. A, 376 (2010) 25–32. [12] L.K. Leong K.S. Chin Y.H. Taufiq-Yap Catal. Today 164 2011 341 346 L.K. Leong, K.S. Chin, Y.H. Taufiq-Yap, Catal. Today, 164 (2011) 341–346. [13] Y.H. Taufiq-Yap S.N. Asrina G.J. Hutchings N.F. Dummer J.K. Bartley J. Nat. Gas Chem. 20 2011 635 638 Y.H. Taufiq-Yap, S.N. Asrina, G.J. Hutchings, N.F. Dummer, J.K. Bartley, J. Nat. Gas Chem., 20 (2011) 635–638. [14] W. Weng R. Al Otaibi M. Alhumaimess M. Conte J.K. Bartley N.F. Dummer G.J. Hutchings C.J. Kiely J. Mater. Chem. 21 2011 W. Weng, R. Al Otaibi, M. Alhumaimess, M. Conte, J.K. Bartley, N.F. Dummer, G.J. Hutchings, C.J. Kiely, J. Mater. Chem., 21 (2011). [15] Y.H. Taufiq-Yap C.S. Yuen N.M.N. Suziana R. Irmawati Chin. J. Catal. 35 2014 270 276 Y.H. Taufiq-Yap, C.S. Yuen, N.M.N. Suziana, R. Irmawati, Chin. J. Catal., 35 (2014) 270–276. [16] V.A. Zazhigalov E.A. Diyuk V.V. Sidorchuk Kinet. Catal. 55 2014 380 389 V.A. Zazhigalov, E.A. Diyuk, V.V. Sidorchuk, Kinet. Catal., 55 (2014) 380–389. [17] R. Berenguer J. Fornells F.J. García-Mateos M.O. Guerrero-Pérez J. Rodríguez-Mirasol T. Cordero Catal. Today 277 2016 266 273 R. Berenguer, J. Fornells, F.J. García-Mateos, M.O. Guerrero-Pérez, J. Rodríguez-Mirasol, T. Cordero, Catal. Today, 277 (2016) 266–273. [18] F. Dai Z. Li X. Chen B. He R. Liu S. Zhang Catal. Sci. Technol. 8 2018 4515 4525 F. Dai, Z. Li, X. Chen, B. He, R. Liu, S. Zhang, Catal. Sci. Technol., 8 (2018) 4515–4525. [19] J. Li P. Yu J. Xie Y. Zhang H. Liu D. Su J. Rong J. Catal. 360 2018 51 56 J. Li, P. Yu, J. Xie, Y. Zhang, H. Liu, D. Su, J. Rong, J. Catal., 360 (2018) 51–56. [20] M. Naseri F. Tahriri Zangeneh A. Taeb Reaction Kinet., Mechan. Cataly. 126 2018 477 495 M. Naseri, F. Tahriri Zangeneh, A. Taeb, Reaction Kinet., Mechan. Cataly., 126 (2018) 477–495. [21] Y. Wang Z. Wang X. Hao W. Zhang W. Zhu Ind. Eng. Chem. Res. 57 2018 12055 12060 Y. Wang, Z. Wang, X. Hao, W. Zhang, W. Zhu, Ind. Eng. Chem. Res., 57 (2018) 12055–12060. [22] B. He Z. Li H. Zhang F. Dai K. Li R. Liu S. Zhang Ind. Eng. Chem. Res. 58 2019 2857 2867 B. He, Z. Li, H. Zhang, F. Dai, K. Li, R. Liu, S. Zhang, Ind. Eng. Chem. Res., 58 (2019) 2857–2867. [23] B. He L. Nan Z. Li B. Wen J. Niu R. Liu ChemistrySelect, 4 2019 662 669 B. He, L. Nan, Z. Li, B. Wen, J. Niu, R. Liu, ChemistrySelect, 4 (2019) 662–669. [24] K. Li B. He J. Liu H. Zhang R. Zhang R. Liu Y.-F. Song S. Zhang Appl. Catal. A 582 2019 K. Li, B. He, J. Liu, H. Zhang, R. Zhang, R. Liu, Y.-F. Song, S. Zhang, Appl. Catal. A, 582 (2019). [25] M.T. Nguyen Dinh T.L. Nguyen M.D. Phan L. Nguyen Dinh Q.D. Truong E. Bordes-Richard J. Catal. 377 2019 638 651 M.T. Nguyen Dinh, T.L. Nguyen, M.D. Phan, L. Nguyen Dinh, Q.D. Truong, E. Bordes-Richard, J. Catal., 377 (2019) 638–651. [26] N.D. Shcherban E.A. Diyuk V.V. Sydorchuk React. Kinet. Mech. Cataly. 126 2019 975 985 N.D. Shcherban, E.A. Diyuk, V.V. Sydorchuk, React. Kinet. Mech. Cataly., 126 (2019) 975–985. [27] Y. Wang Y. Hou X. Hao Z. Wang W. Zhu RSC Adv. 9 2019 5958 5966 Y. Wang, Y. Hou, X. Hao, Z. Wang, W. Zhu, RSC Adv., 9 (2019) 5958–5966. [28] Q. Zhang W. Fang Q. Li Micro Nano Lett. 14 2019 1126 1130 Q. Zhang, W. Fang, Q. Li, Micro Nano Lett., 14 (2019) 1126–1130. [29] F. Dai Y. Shi T. Zhang M. Faizan Z. Li R. Zhang R. Liu S. Zhang Catal. Lett. 151 2020 255 266 F. Dai, Y. Shi, T. Zhang, M. Faizan, Z. Li, R. Zhang, R. Liu, S. Zhang, Catal. Lett., 151 (2020) 255–266. [30] B. He Y. Li T. Zhang Y. Shi K. Li F. Dai R. Zhang R. Liu S. Zhang J. Phys. Chem. B 124 2020 3743 3753 B. He, Y. Li, T. Zhang, Y. Shi, K. Li, F. Dai, R. Zhang, R. Liu, S. Zhang, J. Phys. Chem. B, 124 (2020) 3743–3753. [31] Y. Shi F. Dai T. Zhang B. He R. Zhang R. Liu B. Ren ChemistrySelect 5 2020 6907 6917 Y. Shi, F. Dai, T. Zhang, B. He, R. Zhang, R. Liu, B. Ren, ChemistrySelect, 5 (2020) 6907–6917. [32] M. Faizan R. Zhang R. Liu Catal. Lett. 2022 M. Faizan, R. Zhang, R. Liu, Catal. Lett., (2022). [33] H. Zhang J. Dong Y. Li F. Chen R. Zhang X. Xiang R. Liu J. He S. Zhang Ind. Eng. Chem. Res. 61 2022 3850 3859 H. Zhang, J. Dong, Y. Li, F. Chen, R. Zhang, X. Xiang, R. Liu, J. He, S. Zhang, Ind. Eng. Chem. Res., 61 (2022) 3850–3859. [34] W. Li Y. Xiao S. Guo L. Jia H. Guo D. Li Fuel 333 2023 W. Li, Y. Xiao, S. Guo, L. Jia, H. Guo, D. Li, Fuel, 333 (2023). [35] A.M. Duarte de Farias W.d.A. Gonzalez P.G. Pries de Oliveira J.-G. Eon J.-M. Herrmann M. Aouine S. Loridant J.-C. Volta J. Catal. 208 2002 238 246 A.M. Duarte de Farias, W.d.A. Gonzalez, P.G. Pries de Oliveira, J.-G. Eon, J.-M. Herrmann, M. Aouine, S. Loridant, J.-C. Volta, J. Catal., 208 (2002) 238–246. [36] B.T. Pierini E.A. Lombardo Mater. Chem. Phys. 92 2005 197 204 B.T. Pierini, E.A. Lombardo, Mater. Chem. Phys., 92 (2005) 197–204. [37] L. Zeng H. Jiang J. Niu J. Mol. Catal. A Chem. 232 2005 119 122 L. Zeng, H. Jiang, J. Niu, J. Mol. Catal. A Chem., 232 (2005) 119–122. [38] L. Sartoni A.a. Delimitis J.K. Bartley A. Burrows H. Roussel J.-M. Herrmann J.-C. Volta C.J. Kiely G.J. Hutchings J. Mater. Chem. 16 2006 L. Sartoni, A.a. Delimitis, J.K. Bartley, A. Burrows, H. Roussel, J.-M. Herrmann, J.-C. Volta, C.J. Kiely, G.J. Hutchings, J. Mater. Chem., 16 (2006). [39] A.A. Rownaghi Y.H. Taufiq-Yap F. Rezaei Catal. Lett. 130 2009 504 516 A.A. Rownaghi, Y.H. Taufiq-Yap, F. Rezaei, Catal. Lett., 130 (2009) 504–516. [40] Y.H. Taufiq-Yap C.K. Goh G.J. Hutchings N. Dummer J. Bartley Catal. Lett. 130 2009 327 334 Y.H. Taufiq-Yap, C.K. Goh, G.J. Hutchings, N. Dummer, J. Bartley, Catal. Lett., 130 (2009) 327–334. [41] Y.H. Taufiq-Yap N.M. Nurul Suziana M.Z. Hussein Catal. Lett. 141 2010 136 148 Y.H. Taufiq-Yap, N.M. Nurul Suziana, M.Z. Hussein, Catal. Lett., 141 (2010) 136–148. [42] Y.H. Taufiq-Yap K.L. Theam G.J. Hutchings N. Dummer J.K. Bartley Pet. Sci. Technol. 28 2010 997 1012 Y.H. Taufiq-Yap, K.L. Theam, G.J. Hutchings, N. Dummer, J.K. Bartley, Pet. Sci. Technol., 28 (2010) 997–1012. [43] S. Luciani F. Cavani V. Dal Santo N. Dimitratos M. Rossi C.L. Bianchi Catal. Today 169 2011 200 206 S. Luciani, F. Cavani, V. Dal Santo, N. Dimitratos, M. Rossi, C.L. Bianchi, Catal. Today, 169 (2011) 200–206. [44] A. Caldarelli M.A. Bañares C. Cortelli S. Luciani F. Cavani Catal. Sci. Technol. 4 2014 419 427 A. Caldarelli, M.A. Bañares, C. Cortelli, S. Luciani, F. Cavani, Catal. Sci. Technol., 4 (2014) 419–427. [45] H.-Y. Wu H.-B. Wang X.-H. Liu J.-H. Li M.-H. Yang C.-J. Huang W.-Z. Weng H.-L. Wan Appl. Surf. Sci. 351 2015 243 249 H.-Y. Wu, H.-B. Wang, X.-H. Liu, J.-H. Li, M.-H. Yang, C.-J. Huang, W.-Z. Weng, H.-L. Wan, Appl. Surf. Sci., 351 (2015) 243–249. [46] K.Z. Goo Y.H. Yap K.S. Lin L.K. Leong J. Chin. Chem. Soc. 67 2019 94 102 K.Z. Goo, Y.H. Yap, K.S. Lin, L.K. Leong, J. Chin. Chem. Soc., 67 (2019) 94–102. [47] A. Caldarelli F. Cavani F. Folco S. Luciani C. Cortelli R. Leanza Catal. Today 157 2010 204 210 A. Caldarelli, F. Cavani, F. Folco, S. Luciani, C. Cortelli, R. Leanza, Catal. Today, 157 (2010) 204–210. [48] B.K. Vu M.B. Song I.Y. Ahn Y.-W. Suh D.J. Suh W.-I.L. Kim H.-L. Koh Y.G. Choi E.W. Shin Catal. Today 164 2011 214 220 B.K. Vu, M.B. Song, I.Y. Ahn, Y.-W. Suh, D.J. Suh, W.-I.L. Kim, H.-L. Koh, Y.G. Choi, E.W. Shin, Catal. Today, 164 (2011) 214–220. [49] Q.-H. Shang J.-N. Liu W.-Z. Lang X. Yan X.-J. Guo Y.-J. Guo Ind. Eng. Chem. Res. 60 2021 12811 12820 Q.-H. Shang, J.-N. Liu, W.-Z. Lang, X. Yan, X.-J. Guo, Y.-J. Guo, Ind. Eng. Chem. Res., 60 (2021) 12811–12820. [50] Y. Zhang Y. Zhou J. Shi S. Zhou Z. Zhang S. Zhang M. Guo Fuel Process. Technol. 111 2013 94 104 Y. Zhang, Y. Zhou, J. Shi, S. Zhou, Z. Zhang, S. Zhang, M. Guo, Fuel Process. Technol., 111 (2013) 94–104. [51] J. Liu W. Zhou D. Jiang D. Wang W. Wu Y. Wang X. Ma Catal. Today 368 2021 58 65 J. Liu, W. Zhou, D. Jiang, D. Wang, W. Wu, Y. Wang, X. Ma, Catal. Today, 368 (2021) 58–65. [52] V.N. Kalevaru N. Madaan A. Martin Appl. Catal. A 391 2011 52 62 V.N. Kalevaru, N. Madaan, A. Martin, Appl. Catal. A, 391 (2011) 52–62. [53] H.-Y. Wu P. Jin Y.-f. Sun M.-H. Yang C.-J. Huang W.-Z. Weng H.-L. Wan J. Mol. Catal. A Chem. 414 2016 1 8 H.-Y. Wu, P. Jin, Y.-f. Sun, M.-H. Yang, C.-J. Huang, W.-Z. Weng, H.-L. Wan, J. Mol. Catal. A Chem., 414 (2016) 1–8. [54] X. Zhang H. Wang L. Gou L. Li A. Duan Z. Cao ACS Omega 6 2021 23558 23563 X. Zhang, H. Wang, L. Gou, L. Li, A. Duan, Z. Cao, ACS Omega, 6 (2021) 23558–23563. [55] T. Zhang R. Zhang Y. Zhang Z. Xie Y. Li H. Wu F. Dai R. Liu ChemistrySelect 6 2021 513 521 T. Zhang, R. Zhang, Y. Zhang, Z. Xie, Y. Li, H. Wu, F. Dai, R. Liu, ChemistrySelect, 6 (2021) 513–521. [56] S. Mota M. Abon J.C. Volta J.A. Dalmon J. Catal. 193 2000 308 318 S. Mota, M. Abon, J.C. Volta, J.A. Dalmon, J. Catal., 193 (2000) 308–318. [57] J. Frey C. Lieder T. Schölkopf T. Schleid U. Nieken E. Klemm M. Hunger J. Catal. 272 2010 131 139 J. Frey, C. Lieder, T. Schölkopf, T. Schleid, U. Nieken, E. Klemm, M. Hunger, J. Catal., 272 (2010) 131–139. [58] M.J. Cheng W.A. Goddard 3rd J. Am. Chem. Soc. 135 2013 4600 4603 M.J. Cheng, W.A. Goddard, 3rd, J. Am. Chem. Soc., 135 (2013) 4600–4603. [59] C. Schulz S.C. Roy K. Wittich R.N. d'Alnoncourt S. Linke V.E. Strempel B. Frank R. Glaum F. Rosowski Catal. Today 333 2019 113 119 C. Schulz, S.C. Roy, K. Wittich, R.N. d'Alnoncourt, S. Linke, V.E. Strempel, B. Frank, R. Glaum, F. Rosowski, Catal. Today, 333 (2019) 113–119.",
      "scopus-id": "85162166446",
      "coredata": {
        "eid": "1-s2.0-S2468823123004029",
        "dc:description": "Vanadium phosphorus oxide (VPO) catalyst has been modified by the Ⅲ B elements (Sc, Y, La, Ce) have been prepared. Those catalysts were tested in n-butane selective oxidation, and it was shown that Y-VPO catalyst has the highest maleic anhydride (MA) yield among the studied catalysts. The VPO catalyst was characterized by a series of techniques. As evidenced by property characterization in conjunction with catalytic performance, we found that the presence of rare earth metals alters the phase composition of VPO catalyst. And then, the acidity of VPO catalyst was adjusted. Finally, the change of acidity could impact the n-butane activation process, which affected the n-butane conversion. Moreover, the rare earth metals also modulated the ratio of lattice oxygen and surface oxygen and then the MA selectivity.",
        "openArchiveArticle": "false",
        "prism:coverDate": "2023-08-31",
        "openaccessUserLicense": null,
        "prism:aggregationType": "Journal",
        "prism:url": "https://api.elsevier.com/content/article/pii/S2468823123004029",
        "dc:creator": [
          {
            "@_fa": "true",
            "$": "Li, Wenjiao"
          },
          {
            "@_fa": "true",
            "$": "Guo, Shupeng"
          },
          {
            "@_fa": "true",
            "$": "Guo, Heqin"
          },
          {
            "@_fa": "true",
            "$": "Xiao, Yong"
          },
          {
            "@_fa": "true",
            "$": "Jia, Litao"
          },
          {
            "@_fa": "true",
            "$": "Li, Debao"
          }
        ],
        "link": [
          {
            "@_fa": "true",
            "@rel": "self",
            "@href": "https://api.elsevier.com/content/article/pii/S2468823123004029"
          },
          {
            "@_fa": "true",
            "@rel": "scidir",
            "@href": "https://www.sciencedirect.com/science/article/pii/S2468823123004029"
          }
        ],
        "dc:format": "application/json",
        "openaccessType": null,
        "pii": "S2468-8231(23)00402-9",
        "prism:volume": "547",
        "articleNumber": "113318",
        "prism:publisher": "Elsevier B.V.",
        "dc:title": "Effect of Ⅲ B metals (Sc, Y, La and Ce) on active components regulation of VPO catalyst in n-butane selective oxidation",
        "prism:copyright": "© 2023 Elsevier B.V. All rights reserved.",
        "openaccess": "0",
        "prism:issn": "24688231",
        "dcterms:subject": [
          {
            "@_fa": "true",
            "$": "Rare earth metal"
          },
          {
            "@_fa": "true",
            "$": "VPO catalyst"
          },
          {
            "@_fa": "true",
            "$": "N-butane oxidation"
          },
          {
            "@_fa": "true",
            "$": "MA"
          }
        ],
        "openaccessArticle": "false",
        "prism:publicationName": "Molecular Catalysis",
        "openaccessSponsorType": null,
        "prism:pageRange": "113318",
        "pubType": "fla",
        "prism:coverDisplayDate": "August 2023",
        "prism:doi": "10.1016/j.mcat.2023.113318",
        "prism:startingPage": "113318",
        "dc:identifier": "doi:10.1016/j.mcat.2023.113318",
        "openaccessSponsorName": null
      },
      "objects": {
        "object": [
          {
            "@category": "standard",
            "@height": "298",
            "@width": "565",
            "@_fa": "true",
            "$": "https://api.elsevier.com/content/object/eid/1-s2.0-S2468823123004029-gr1.jpg?httpAccept=%2A%2F%2A",
            "@multimediatype": "JPEG image file",
            "@type": "IMAGE-DOWNSAMPLED",
            "@size": "77149",
            "@ref": "gr1",
            "@mimetype": "image/jpeg"
          },
          {
            "@category": "standard",
            "@height": "216",
            "@width": "565",
            "@_fa": "true",
            "$": "https://api.elsevier.com/content/object/eid/1-s2.0-S2468823123004029-gr7.jpg?httpAccept=%2A%2F%2A",
            "@multimediatype": "JPEG image file",
            "@type": "IMAGE-DOWNSAMPLED",
            "@size": "35512",
            "@ref": "gr7",
            "@mimetype": "image/jpeg"
          },
          {
            "@category": "standard",
            "@height": "202",
            "@width": "565",
            "@_fa": "true",
            "$": "https://api.elsevier.com/content/object/eid/1-s2.0-S2468823123004029-gr6.jpg?httpAccept=%2A%2F%2A",
            "@multimediatype": "JPEG image file",
            "@type": "IMAGE-DOWNSAMPLED",
            "@size": "33453",
            "@ref": "gr6",
            "@mimetype": "image/jpeg"
          },
          {
            "@category": "standard",
            "@height": "304",
            "@width": "320",
            "@_fa": "true",
            "$": "https://api.elsevier.com/content/object/eid/1-s2.0-S2468823123004029-gr5.jpg?httpAccept=%2A%2F%2A",
            "@multimediatype": "JPEG image file",
            "@type": "IMAGE-DOWNSAMPLED",
            "@size": "41584",
            "@ref": "gr5",
            "@mimetype": "image/jpeg"
          },
          {
            "@category": "standard",
            "@height": "313",
            "@width": "527",
            "@_fa": "true",
            "$": "https://api.elsevier.com/content/object/eid/1-s2.0-S2468823123004029-gr4.jpg?httpAccept=%2A%2F%2A",
            "@multimediatype": "JPEG image file",
            "@type": "IMAGE-DOWNSAMPLED",
            "@size": "67755",
            "@ref": "gr4",
            "@mimetype": "image/jpeg"
          },
          {
            "@category": "standard",
            "@height": "335",
            "@width": "386",
            "@_fa": "true",
            "$": "https://api.elsevier.com/content/object/eid/1-s2.0-S2468823123004029-gr3.jpg?httpAccept=%2A%2F%2A",
            "@multimediatype": "JPEG image file",
            "@type": "IMAGE-DOWNSAMPLED",
            "@size": "42014",
            "@ref": "gr3",
            "@mimetype": "image/jpeg"
          },
          {
            "@category": "standard",
            "@height": "564",
            "@width": "565",
            "@_fa": "true",
            "$": "https://api.elsevier.com/content/object/eid/1-s2.0-S2468823123004029-gr2.jpg?httpAccept=%2A%2F%2A",
            "@multimediatype": "JPEG image file",
            "@type": "IMAGE-DOWNSAMPLED",
            "@size": "98554",
            "@ref": "gr2",
            "@mimetype": "image/jpeg"
          },
          {
            "@category": "standard",
            "@height": "200",
            "@width": "356",
            "@_fa": "true",
            "$": "https://api.elsevier.com/content/object/eid/1-s2.0-S2468823123004029-ga1.jpg?httpAccept=%2A%2F%2A",
            "@multimediatype": "JPEG image file",
            "@type": "IMAGE-DOWNSAMPLED",
            "@size": "32815",
            "@ref": "ga1",
            "@mimetype": "image/jpeg"
          },
          {
            "@category": "thumbnail",
            "@height": "115",
            "@width": "219",
            "@_fa": "true",
            "$": "https://api.elsevier.com/content/object/eid/1-s2.0-S2468823123004029-gr1.sml?httpAccept=%2A%2F%2A",
            "@multimediatype": "GIF image file",
            "@type": "IMAGE-THUMBNAIL",
            "@size": "21347",
            "@ref": "gr1",
            "@mimetype": "image/gif"
          },
          {
            "@category": "thumbnail",
            "@height": "84",
            "@width": "219",
            "@_fa": "true",
            "$": "https://api.elsevier.com/content/object/eid/1-s2.0-S2468823123004029-gr7.sml?httpAccept=%2A%2F%2A",
            "@multimediatype": "GIF image file",
            "@type": "IMAGE-THUMBNAIL",
            "@size": "7737",
            "@ref": "gr7",
            "@mimetype": "image/gif"
          },
          {
            "@category": "thumbnail",
            "@height": "78",
            "@width": "219",
            "@_fa": "true",
            "$": "https://api.elsevier.com/content/object/eid/1-s2.0-S2468823123004029-gr6.sml?httpAccept=%2A%2F%2A",
            "@multimediatype": "GIF image file",
            "@type": "IMAGE-THUMBNAIL",
            "@size": "7347",
            "@ref": "gr6",
            "@mimetype": "image/gif"
          },
          {
            "@category": "thumbnail",
            "@height": "164",
            "@width": "172",
            "@_fa": "true",
            "$": "https://api.elsevier.com/content/object/eid/1-s2.0-S2468823123004029-gr5.sml?httpAccept=%2A%2F%2A",
            "@multimediatype": "GIF image file",
            "@type": "IMAGE-THUMBNAIL",
            "@size": "11907",
            "@ref": "gr5",
            "@mimetype": "image/gif"
          },
          {
            "@category": "thumbnail",
            "@height": "130",
            "@width": "219",
            "@_fa": "true",
            "$": "https://api.elsevier.com/content/object/eid/1-s2.0-S2468823123004029-gr4.sml?httpAccept=%2A%2F%2A",
            "@multimediatype": "GIF image file",
            "@type": "IMAGE-THUMBNAIL",
            "@size": "13754",
            "@ref": "gr4",
            "@mimetype": "image/gif"
          },
          {
            "@category": "thumbnail",
            "@height": "164",
            "@width": "189",
            "@_fa": "true",
            "$": "https://api.elsevier.com/content/object/eid/1-s2.0-S2468823123004029-gr3.sml?httpAccept=%2A%2F%2A",
            "@multimediatype": "GIF image file",
            "@type": "IMAGE-THUMBNAIL",
            "@size": "10029",
            "@ref": "gr3",
            "@mimetype": "image/gif"
          },
          {
            "@category": "thumbnail",
            "@height": "164",
            "@width": "164",
            "@_fa": "true",
            "$": "https://api.elsevier.com/content/object/eid/1-s2.0-S2468823123004029-gr2.sml?httpAccept=%2A%2F%2A",
            "@multimediatype": "GIF image file",
            "@type": "IMAGE-THUMBNAIL",
            "@size": "16147",
            "@ref": "gr2",
            "@mimetype": "image/gif"
          },
          {
            "@category": "thumbnail",
            "@height": "123",
            "@width": "219",
            "@_fa": "true",
            "$": "https://api.elsevier.com/content/object/eid/1-s2.0-S2468823123004029-ga1.sml?httpAccept=%2A%2F%2A",
            "@multimediatype": "GIF image file",
            "@type": "IMAGE-THUMBNAIL",
            "@size": "14943",
            "@ref": "ga1",
            "@mimetype": "image/gif"
          },
          {
            "@category": "high",
            "@height": "1317",
            "@width": "2500",
            "@_fa": "true",
            "$": "https://api.elsevier.com/content/object/eid/1-s2.0-S2468823123004029-gr1_lrg.jpg?httpAccept=%2A%2F%2A",
            "@multimediatype": "JPEG image file",
            "@type": "IMAGE-HIGH-RES",
            "@size": "593191",
            "@ref": "gr1",
            "@mimetype": "image/jpeg"
          },
          {
            "@category": "high",
            "@height": "957",
            "@width": "2500",
            "@_fa": "true",
            "$": "https://api.elsevier.com/content/object/eid/1-s2.0-S2468823123004029-gr7_lrg.jpg?httpAccept=%2A%2F%2A",
            "@multimediatype": "JPEG image file",
            "@type": "IMAGE-HIGH-RES",
            "@size": "218837",
            "@ref": "gr7",
            "@mimetype": "image/jpeg"
          },
          {
            "@category": "high",
            "@height": "893",
            "@width": "2500",
            "@_fa": "true",
            "$": "https://api.elsevier.com/content/object/eid/1-s2.0-S2468823123004029-gr6_lrg.jpg?httpAccept=%2A%2F%2A",
            "@multimediatype": "JPEG image file",
            "@type": "IMAGE-HIGH-RES",
            "@size": "206018",
            "@ref": "gr6",
            "@mimetype": "image/jpeg"
          },
          {
            "@category": "high",
            "@height": "1348",
            "@width": "1417",
            "@_fa": "true",
            "$": "https://api.elsevier.com/content/object/eid/1-s2.0-S2468823123004029-gr5_lrg.jpg?httpAccept=%2A%2F%2A",
            "@multimediatype": "JPEG image file",
            "@type": "IMAGE-HIGH-RES",
            "@size": "264594",
            "@ref": "gr5",
            "@mimetype": "image/jpeg"
          },
          {
            "@category": "high",
            "@height": "1386",
            "@width": "2333",
            "@_fa": "true",
            "$": "https://api.elsevier.com/content/object/eid/1-s2.0-S2468823123004029-gr4_lrg.jpg?httpAccept=%2A%2F%2A",
            "@multimediatype": "JPEG image file",
            "@type": "IMAGE-HIGH-RES",
            "@size": "470023",
            "@ref": "gr4",
            "@mimetype": "image/jpeg"
          },
          {
            "@category": "high",
            "@height": "1483",
            "@width": "1708",
            "@_fa": "true",
            "$": "https://api.elsevier.com/content/object/eid/1-s2.0-S2468823123004029-gr3_lrg.jpg?httpAccept=%2A%2F%2A",
            "@multimediatype": "JPEG image file",
            "@type": "IMAGE-HIGH-RES",
            "@size": "245999",
            "@ref": "gr3",
            "@mimetype": "image/jpeg"
          },
          {
            "@category": "high",
            "@height": "2495",
            "@width": "2500",
            "@_fa": "true",
            "$": "https://api.elsevier.com/content/object/eid/1-s2.0-S2468823123004029-gr2_lrg.jpg?httpAccept=%2A%2F%2A",
            "@multimediatype": "JPEG image file",
            "@type": "IMAGE-HIGH-RES",
            "@size": "738945",
            "@ref": "gr2",
            "@mimetype": "image/jpeg"
          },
          {
            "@category": "high",
            "@height": "886",
            "@width": "1576",
            "@_fa": "true",
            "$": "https://api.elsevier.com/content/object/eid/1-s2.0-S2468823123004029-ga1_lrg.jpg?httpAccept=%2A%2F%2A",
            "@multimediatype": "JPEG image file",
            "@type": "IMAGE-HIGH-RES",
            "@size": "265825",
            "@ref": "ga1",
            "@mimetype": "image/jpeg"
          },
          {
            "@category": "standard",
            "@_fa": "true",
            "$": "https://api.elsevier.com/content/object/eid/1-s2.0-S2468823123004029-am.pdf?httpAccept=%2A%2F%2A",
            "@multimediatype": "Acrobat PDF file",
            "@type": "AAM-PDF",
            "@size": "586334",
            "@ref": "am",
            "@mimetype": "application/pdf"
          }
        ]
      },
      "link": {
        "@rel": "abstract",
        "@href": "https://api.elsevier.com/content/abstract/scopus_id/85162166446"
      }
    }
  }
}